fractal/cli/__init__.py
fractal/cli/__main__.py
fractal/cli/controllers/__init__.py
fractal/cli/controllers/auth.py
fractal/cli/controllers/registration.py
fractal/cli/fmt.py
fractal/cli/utils.py
fractal_cli-0.1.3.dist-info/LICENSE
fractal_cli-0.1.3.dist-info/METADATA
fractal_cli-0.1.3.dist-info/WHEEL
fractal_cli-0.1.3.dist-info/entry_points.txt
fractal_cli-0.1.3.dist-info/RECORD
