Metadata-Version: 2.1
Name: fractal-cli
Version: 0.1.3
Summary: 
Author: Mo Balaa
Author-email: balaa@fractalnetworks.co
Requires-Python: >=3.10,<4.0
Classifier: Programming Language :: Python :: 3
Classifier: Programming Language :: Python :: 3.10
Classifier: Programming Language :: Python :: 3.11
Classifier: Programming Language :: Python :: 3.12
Provides-Extra: dev
Requires-Dist: appdirs (>=1.4.4,<2.0.0)
Requires-Dist: asgiref (>=3.7.2)
Requires-Dist: clicz (>=0.0.2)
Requires-Dist: docker (>=6.1.3,<7.0.0) ; extra == "dev"
Requires-Dist: fractal-matrix-client (>=0.0.1)
Requires-Dist: ipython (>=8.17.2,<9.0.0) ; extra == "dev"
Requires-Dist: pytest (>=7.4.3,<8.0.0) ; extra == "dev"
Requires-Dist: pytest-asyncio (>=0.21.1,<0.22.0) ; extra == "dev"
Requires-Dist: pytest-cov (>=4.1.0,<5.0.0) ; extra == "dev"
Requires-Dist: pytest-mock (>=3.11.1,<4.0.0) ; extra == "dev"
Requires-Dist: pyyaml (>=6.0.1,<7.0.0)
Requires-Dist: rich (>=12.6.0)
Requires-Dist: toml (>=0.10.2,<0.11.0)
